camelids/__init__.py
camelids/adapter.py
camelids/rest.py
camelids-0.0.6.dist-info/licenses/LICENSE
camelids-0.0.6.dist-info/METADATA
camelids-0.0.6.dist-info/WHEEL
camelids-0.0.6.dist-info/top_level.txt
camelids-0.0.6.dist-info/RECORD
